peu/__init__.py
peu/core.py
peu/multi.py
peu_bandoos-0.0.2.dist-info/LICENSE
peu_bandoos-0.0.2.dist-info/METADATA
peu_bandoos-0.0.2.dist-info/WHEEL
peu_bandoos-0.0.2.dist-info/top_level.txt
peu_bandoos-0.0.2.dist-info/RECORD
