Metadata-Version: 2.1
Name: peu-bandoos
Version: 0.0.2
Summary: Python experiment utils
Home-page: https://github.com/bandoos/peu
Author: Luca Bandelli
Author-email: bandoos42@gmail.com
License: UNKNOWN
Project-URL: Bug Tracker, https://github.com/bandoos/peu/issues
Platform: UNKNOWN
Classifier: Programming Language :: Python :: 3
Classifier: License :: OSI Approved :: MIT License
Classifier: Operating System :: OS Independent
Requires-Python: >=3.6
License-File: LICENSE
Requires-Dist: tqdm
